django_firebase_scrypt/__init__.py
django_firebase_scrypt/hashers.py
django_firebase_scrypt-0.0.2.dist-info/LICENSE
django_firebase_scrypt-0.0.2.dist-info/METADATA
django_firebase_scrypt-0.0.2.dist-info/WHEEL
django_firebase_scrypt-0.0.2.dist-info/top_level.txt
django_firebase_scrypt-0.0.2.dist-info/RECORD
