Metadata-Version: 2.1
Name: django-firebase-scrypt
Version: 0.0.2
Summary: A Django password hasher to use for users imported from Firebase
Home-page: https://github.com/mcsimps2/django-firebase-scrypt
Author: Matthew Simpson
Author-email: mcsimps2@gmail.com
License: UNKNOWN
Platform: UNKNOWN
Classifier: Programming Language :: Python :: 3
Classifier: Operating System :: OS Independent
Classifier: Framework :: Django :: 3.0
Classifier: License :: OSI Approved :: MIT License
Requires-Dist: pyscryptfirebase
